igv/.gitignore
igv/__init__.py
igv/browser.py
igv/labextension.py
igv/tool.py
igv/version.py
igv/labextension/package.json
igv/labextension/schemas/@igvteam/igv-jupyter/package.json.orig
igv/labextension/static/568.867ca2f63df7597bf631.js
igv/labextension/static/627.fd0b75f10c8c5bf0b324.js
igv/labextension/static/627.fd0b75f10c8c5bf0b324.js.LICENSE.txt
igv/labextension/static/remoteEntry.158175185bd8feaf809f.js
igv/labextension/static/style.js
igv/nbextension/__init__.py
igv/nbextension/static/extension.js
igv/nbextension/static/index.js
igv/nbextension/static/igvjs/igv.js
igv-0.10.0.data/data/share/jupyter/labextensions/@igvteam/igv-jupyter/install.json
igv-0.10.0.data/data/share/jupyter/labextensions/@igvteam/igv-jupyter/package.json
igv-0.10.0.data/data/share/jupyter/labextensions/@igvteam/igv-jupyter/schemas/@igvteam/igv-jupyter/package.json.orig
igv-0.10.0.data/data/share/jupyter/labextensions/@igvteam/igv-jupyter/static/568.867ca2f63df7597bf631.js
igv-0.10.0.data/data/share/jupyter/labextensions/@igvteam/igv-jupyter/static/627.fd0b75f10c8c5bf0b324.js
igv-0.10.0.data/data/share/jupyter/labextensions/@igvteam/igv-jupyter/static/627.fd0b75f10c8c5bf0b324.js.LICENSE.txt
igv-0.10.0.data/data/share/jupyter/labextensions/@igvteam/igv-jupyter/static/remoteEntry.158175185bd8feaf809f.js
igv-0.10.0.data/data/share/jupyter/labextensions/@igvteam/igv-jupyter/static/style.js
igv-0.10.0.data/data/share/jupyter/nbextensions/igv/extension.js
igv-0.10.0.data/data/share/jupyter/nbextensions/igv/index.js
igv-0.10.0.data/data/share/jupyter/nbextensions/igv/igvjs/igv.js
igv-0.10.0.data/data/share/jupyter/nbtools/igv.json
igv-0.10.0.dist-info/LICENSE.md
igv-0.10.0.dist-info/METADATA
igv-0.10.0.dist-info/WHEEL
igv-0.10.0.dist-info/top_level.txt
igv-0.10.0.dist-info/RECORD
