Metadata-Version: 2.1
Name: igv
Version: 0.10.0
Summary: Jupyter extension for embedding the igv.js genome visualization in a notebook
Home-page: https://github.com/igvteam/igv-jupyter
Author: Thorin Tabor
Author-email: tmtabor@cloud.ucsd.edu
License: MIT
Keywords: igv,bioinformatics,genomics,visualization,Jupyter,JupyterLab,JupyterLab3
Platform: Linux
Platform: Mac OS X
Platform: Windows
Classifier: Intended Audience :: Developers
Classifier: Intended Audience :: Science/Research
Classifier: License :: OSI Approved :: MIT License
Classifier: Programming Language :: Python
Classifier: Programming Language :: Python :: 3
Classifier: Programming Language :: Python :: 3.6
Classifier: Programming Language :: Python :: 3.7
Classifier: Programming Language :: Python :: 3.8
Classifier: Programming Language :: Python :: 3.9
Classifier: Framework :: Jupyter
Requires-Python: >=3.6
Requires-Dist: jupyterlab (~=3.0)
Requires-Dist: ipywidgets (>=7.0.0)
